Metadata-Version: 2.1
Name: gb-probability-dist
Version: 1.3
Summary: Gaussian and Binomial distributions
Home-page: UNKNOWN
Author: Anthony Miranda
Author-email: anthonymirandagil@gmail.com
License: UNKNOWN
Platform: UNKNOWN
